monitor_summer_snapshots/config.yml.example
monitor_summer_snapshots/graphana_dashboard.json
monitor_summer_snapshots/logger.conf
monitor_summer_snapshots/monitor_summer_snapshots.py
monitor_summer_snapshots/zabbix_discovery.py
monitor_summer_snapshots/zabbix_template.xml
monitor_summer_snapshots-0.7.2.dist-info/LICENSE
monitor_summer_snapshots-0.7.2.dist-info/METADATA
monitor_summer_snapshots-0.7.2.dist-info/WHEEL
monitor_summer_snapshots-0.7.2.dist-info/entry_points.txt
monitor_summer_snapshots-0.7.2.dist-info/RECORD
