Metadata-Version: 2.1
Name: monitor-summer-snapshots
Version: 0.7.2
Summary: 
Home-page: https://gricad-gitlab.univ-grenoble-alpes.fr/OSUG/RESIF/monitor-summer-snapshots
Author: Jonathan Schaeffer
Author-email: jonathan.schaeffer@univ-grenoble-alpes.fr
Classifier: Programming Language :: Python :: 2
Classifier: Programming Language :: Python :: 2.7
Classifier: Programming Language :: Python :: 3
Classifier: Programming Language :: Python :: 3.4
Classifier: Programming Language :: Python :: 3.5
Classifier: Programming Language :: Python :: 3.6
Classifier: Programming Language :: Python :: 3.7
Classifier: Programming Language :: Python :: 3.8
Classifier: Programming Language :: Python :: 3.9
Classifier: Programming Language :: Python :: 3.10
Classifier: Programming Language :: Python :: 3.11
Requires-Dist: influxdb
Requires-Dist: paramiko
Requires-Dist: py-zabbix
Requires-Dist: pyyaml
